{
  "SJML": {
    "header": {
      "identifier": "텍스트_구어체 말뭉치 구축_0001673036",
      "name": "컨테이너 텍스트 인식을 위한 학습용 데이터셋",
      "type": "0",
      "source_file": "BOIB210001673036"
    },
    "text": [
      {
        "content": "이것도 재미있지",
        "writer": "UgwBurVchPfRuaKjt3d4AaABAg",
        "write_date": "2021-10-12",
        "url": "https://www.youtube.com/channel/UCBkyj16n2snkRg1BAzpovXQ",
        "parent_url": "https://www.youtube.com/watch?v=hi9nDUwwYWc",
        "source_site": "https://www.youtube.com/"
      },
      {
        "content": "찾아봐는데없어요 어떻하죠 하고싶은데",
        "writer": "Ugxksu1Ar0mWTeYKc7h4AaABAg",
        "write_date": "2021-04-12",
        "url": "https://www.youtube.com/channel/UCBkyj16n2snkRg1BAzpovXQ",
        "parent_url": "https://www.youtube.com/watch?v=hi9nDUwwYWc",
        "source_site": "https://www.youtube.com/"
      },
      {
        "content": "제발, 래티캐티 같이 할사람,",
        "writer": "UgzLRNNGgQC_-uIv4YV4AaABAg",
        "write_date": "2021-03-12",
        "url": "https://www.youtube.com/channel/UCBkyj16n2snkRg1BAzpovXQ",
        "parent_url": "https://www.youtube.com/watch?v=hi9nDUwwYWc",
        "source_site": "https://www.youtube.com/"
      },
      {
        "content": "저 게임이 스위트홈 원조네",
        "writer": "UgyM18MtjbXJXX4jD-J4AaABAg",
        "write_date": "2021-03-12",
        "url": "https://www.youtube.com/channel/UCBkyj16n2snkRg1BAzpovXQ",
        "parent_url": "https://www.youtube.com/watch?v=hi9nDUwwYWc",
        "source_site": "https://www.youtube.com/"
      },
      {
        "content": "처음부터 편애하는 편애좌,",
        "writer": "UgxNDTTbtHA9a6evcGl4AaABAg",
        "write_date": "2021-02-12",
        "url": "https://www.youtube.com/channel/UCBkyj16n2snkRg1BAzpovXQ",
        "parent_url": "https://www.youtube.com/watch?v=hi9nDUwwYWc",
        "source_site": "https://www.youtube.com/"
      },
      {
        "content": "올만에 보니까 또 재밌당",
        "writer": "UgzcXk0sKr_1fVmOnSV4AaABAg",
        "write_date": "2021-02-12",
        "url": "https://www.youtube.com/channel/UCBkyj16n2snkRg1BAzpovXQ",
        "parent_url": "https://www.youtube.com/watch?v=hi9nDUwwYWc",
        "source_site": "https://www.youtube.com/"
      },
      {
        "content": "재밌었어 이거",
        "writer": "UgzTeVR4QEqtGaxpaEZ4AaABAg",
        "write_date": "2021-01-12",
        "url": "https://www.youtube.com/channel/UCBkyj16n2snkRg1BAzpovXQ",
        "parent_url": "https://www.youtube.com/watch?v=hi9nDUwwYWc",
        "source_site": "https://www.youtube.com/"
      },
      {
        "content": "오랜만에 보러왔는데 준나 재밌네",
        "writer": "Ugyh7oDb9bjl2KJS8V54AaABAg",
        "write_date": "2020-12-12",
        "url": "https://www.youtube.com/channel/UCBkyj16n2snkRg1BAzpovXQ",
        "parent_url": "https://www.youtube.com/watch?v=hi9nDUwwYWc",
        "source_site": "https://www.youtube.com/"
      },
      {
        "content": "이거 언제 한번 다시 (이름)나 진짜 (비속어)잼이였는데",
        "writer": "Ugz-HTUXCLrY_1C4L3h4AaABAg",
        "write_date": "2020-11-12",
        "url": "https://www.youtube.com/channel/UCBkyj16n2snkRg1BAzpovXQ",
        "parent_url": "https://www.youtube.com/watch?v=hi9nDUwwYWc",
        "source_site": "https://www.youtube.com/"
      },
      {
        "content": "이영상 처음 올라왔을때 한동안 이것만 맨날 봤었는데 오랜만에 추천동영상으로 떳네요 다시봐도 재밌어",
        "writer": "UgzTCZe8-eMsiNBnUrh4AaABAg",
        "write_date": "2020-11-12",
        "url": "https://www.youtube.com/channel/UCBkyj16n2snkRg1BAzpovXQ",
        "parent_url": "https://www.youtube.com/watch?v=hi9nDUwwYWc",
        "source_site": "https://www.youtube.com/"
      },
      {
        "content": "아니 왼쪽 위에 맵이 있는데,",
        "writer": "Ugy6x_aLFGcgM5YvGjp4AaABAg",
        "write_date": "2020-11-12",
        "url": "https://www.youtube.com/channel/UCBkyj16n2snkRg1BAzpovXQ",
        "parent_url": "https://www.youtube.com/watch?v=hi9nDUwwYWc",
        "source_site": "https://www.youtube.com/"
      },
      {
        "content": "아 진짜 너무 재밌네 첨에 별 기대 안하고 봤는데",
        "writer": "UgwLI8LhFOXKon6OhY14AaABAg",
        "write_date": "2020-11-12",
        "url": "https://www.youtube.com/channel/UCBkyj16n2snkRg1BAzpovXQ",
        "parent_url": "https://www.youtube.com/watch?v=hi9nDUwwYWc",
        "source_site": "https://www.youtube.com/"
      },
      {
        "content": "형 광고가 너무 많아,",
        "writer": "Ugx1bUOJC7lL7Zh68Jp4AaABAg",
        "write_date": "2020-11-12",
        "url": "https://www.youtube.com/channel/UCBkyj16n2snkRg1BAzpovXQ",
        "parent_url": "https://www.youtube.com/watch?v=hi9nDUwwYWc",
        "source_site": "https://www.youtube.com/"
      },
      {
        "content": "와, 이게 벌써 거의 3년이 됐넼 이걸로 왁굳형 입문했는데",
        "writer": "UgyP4cfGgHgsbyl-wC94AaABAg",
        "write_date": "2020-11-12",
        "url": "https://www.youtube.com/channel/UCBkyj16n2snkRg1BAzpovXQ",
        "parent_url": "https://www.youtube.com/watch?v=hi9nDUwwYWc",
        "source_site": "https://www.youtube.com/"
      },
      {
        "content": "썸넬보고 키즈유튜브인줄 발",
        "writer": "Ugxy_FORcrF3gaV0eAB4AaABAg",
        "write_date": "2020-11-12",
        "url": "https://www.youtube.com/channel/UCBkyj16n2snkRg1BAzpovXQ",
        "parent_url": "https://www.youtube.com/watch?v=hi9nDUwwYWc",
        "source_site": "https://www.youtube.com/"
      },
      {
        "content": "내가 남긴줄",
        "writer": "Ugyh7oDb9bjl2KJS8V54AaABAg.9GMKGs9SAU29NRraJEpbjU",
        "write_date": "2021-06-12",
        "url": "https://www.youtube.com/channel/UCBkyj16n2snkRg1BAzpovXQ",
        "parent_url": "https://www.youtube.com/watch?v=hi9nDUwwYWc",
        "source_site": "https://www.youtube.com/"
      },
      {
        "content": "신난거 너무귀엽잖앜",
        "writer": "Ugy1XCywaQLTycCUqXZ4AaABAg",
        "write_date": "2020-11-12",
        "url": "https://www.youtube.com/channel/UCBkyj16n2snkRg1BAzpovXQ",
        "parent_url": "https://www.youtube.com/watch?v=hi9nDUwwYWc",
        "source_site": "https://www.youtube.com/"
      },
      {
        "content": "고양이는 컴퓨터인가여 유저인가요 레알 고양이 무섭게 생김, 무서운란란루 급",
        "writer": "UgxqjUNkBfNLtPjkrHR4AaABAg",
        "write_date": "2020-11-12",
        "url": "https://www.youtube.com/channel/UCBkyj16n2snkRg1BAzpovXQ",
        "parent_url": "https://www.youtube.com/watch?v=hi9nDUwwYWc",
        "source_site": "https://www.youtube.com/"
      },
      {
        "content": "역시 이 형은 (비속어)믈리에야",
        "writer": "UgxJKZtEJavdCHQT4sl4AaABAg",
        "write_date": "2020-11-12",
        "url": "https://www.youtube.com/channel/UCBkyj16n2snkRg1BAzpovXQ",
        "parent_url": "https://www.youtube.com/watch?v=hi9nDUwwYWc",
        "source_site": "https://www.youtube.com/"
      },
      {
        "content": "넘모 재밋어",
        "writer": "UgylgDs9F9v0WjLetll4AaABAg",
        "write_date": "2020-11-12",
        "url": "https://www.youtube.com/channel/UCBkyj16n2snkRg1BAzpovXQ",
        "parent_url": "https://www.youtube.com/watch?v=hi9nDUwwYWc",
        "source_site": "https://www.youtube.com/"
      },
      {
        "content": "광고 (이름)요",
        "writer": "UgyDkHTMW7BNDsZYwI94AaABAg",
        "write_date": "2020-11-12",
        "url": "https://www.youtube.com/channel/UCBkyj16n2snkRg1BAzpovXQ",
        "parent_url": "https://www.youtube.com/watch?v=hi9nDUwwYWc",
        "source_site": "https://www.youtube.com/"
      },
      {
        "content": "계속 그대를 만난대 어딜",
        "writer": "UgwYPv85HwG-7CqLedh4AaABAg",
        "write_date": "2020-11-12",
        "url": "https://www.youtube.com/channel/UCBkyj16n2snkRg1BAzpovXQ",
        "parent_url": "https://www.youtube.com/watch?v=hi9nDUwwYWc",
        "source_site": "https://www.youtube.com/"
      },
      {
        "content": "형 언제한번 이게임 다시가자 진짜",
        "writer": "UgyzEIGqADjVx0pGuzV4AaABAg",
        "write_date": "2020-11-12",
        "url": "https://www.youtube.com/channel/UCBkyj16n2snkRg1BAzpovXQ",
        "parent_url": "https://www.youtube.com/watch?v=hi9nDUwwYWc",
        "source_site": "https://www.youtube.com/"
      },
      {
        "content": "형, 광고 토나와",
        "writer": "UgzRX-F3CaLVirPRtN94AaABAg",
        "write_date": "2019-11-12",
        "url": "https://www.youtube.com/channel/UCBkyj16n2snkRg1BAzpovXQ",
        "parent_url": "https://www.youtube.com/watch?v=hi9nDUwwYWc",
        "source_site": "https://www.youtube.com/"
      },
      {
        "content": "치질 와 진짜 재밌다",
        "writer": "UgzEMg2sZ65e392h-N14AaABAg",
        "write_date": "2019-11-12",
        "url": "https://www.youtube.com/channel/UCBkyj16n2snkRg1BAzpovXQ",
        "parent_url": "https://www.youtube.com/watch?v=hi9nDUwwYWc",
        "source_site": "https://www.youtube.com/"
      },
      {
        "content": "왁굳형의 왛이히히히힣 그거 듣는순간 오늘 동영상 다봤다",
        "writer": "Ugz0KSTuxQijUhVKJ9B4AaABAg",
        "write_date": "2019-11-12",
        "url": "https://www.youtube.com/channel/UCBkyj16n2snkRg1BAzpovXQ",
        "parent_url": "https://www.youtube.com/watch?v=hi9nDUwwYWc",
        "source_site": "https://www.youtube.com/"
      },
      {
        "content": "이거 (이름) 구독했습니당",
        "writer": "UgzDeeiHtWbvIlccXZ14AaABAg",
        "write_date": "2019-11-12",
        "url": "https://www.youtube.com/channel/UCBkyj16n2snkRg1BAzpovXQ",
        "parent_url": "https://www.youtube.com/watch?v=hi9nDUwwYWc",
        "source_site": "https://www.youtube.com/"
      },
      {
        "content": "어으 (비속어) (비속어) 답답허네 겜좀 잘해줘",
        "writer": "UgzSotsM6_uwT9b_9Op4AaABAg",
        "write_date": "2019-11-12",
        "url": "https://www.youtube.com/channel/UCBkyj16n2snkRg1BAzpovXQ",
        "parent_url": "https://www.youtube.com/watch?v=hi9nDUwwYWc",
        "source_site": "https://www.youtube.com/"
      },
      {
        "content": "여기서부터가 하이라이트",
        "writer": "UgxQvji3Op1dTu8pimR4AaABAg",
        "write_date": "2019-11-12",
        "url": "https://www.youtube.com/channel/UCBkyj16n2snkRg1BAzpovXQ",
        "parent_url": "https://www.youtube.com/watch?v=hi9nDUwwYWc",
        "source_site": "https://www.youtube.com/"
      },
      {
        "content": "이제 그대랑 만나지말게.",
        "writer": "UgxbP2_3k584epf-Agd4AaABAg",
        "write_date": "2019-11-12",
        "url": "https://www.youtube.com/channel/UCBkyj16n2snkRg1BAzpovXQ",
        "parent_url": "https://www.youtube.com/watch?v=hi9nDUwwYWc",
        "source_site": "https://www.youtube.com/"
      },
      {
        "content": "이거 또 했음 좋겠다 쥐할때 꿀잼",
        "writer": "UgwnFnWIN49mfYQy30x4AaABAg",
        "write_date": "2019-11-12",
        "url": "https://www.youtube.com/channel/UCBkyj16n2snkRg1BAzpovXQ",
        "parent_url": "https://www.youtube.com/watch?v=hi9nDUwwYWc",
        "source_site": "https://www.youtube.com/"
      },
      {
        "content": "앙(비속어) 너무 아늑해 계속 돌려보네 개커여미",
        "writer": "UgxYIeljlJZWDryr9bx4AaABAg",
        "write_date": "2019-11-12",
        "url": "https://www.youtube.com/channel/UCBkyj16n2snkRg1BAzpovXQ",
        "parent_url": "https://www.youtube.com/watch?v=hi9nDUwwYWc",
        "source_site": "https://www.youtube.com/"
      },
      {
        "content": "당구 큐대로, 사람도 잡겟네,",
        "writer": "UgybslDZiMneTdh4Ohx4AaABAg",
        "write_date": "2019-11-12",
        "url": "https://www.youtube.com/channel/UCBkyj16n2snkRg1BAzpovXQ",
        "parent_url": "https://www.youtube.com/watch?v=hi9nDUwwYWc",
        "source_site": "https://www.youtube.com/"
      },
      {
        "content": "방에서 혼자 몰폰 하고있었는데 갑자기 에서 그대를 만나고오오 이래서 갑자기 뿜어섴 들킴,",
        "writer": "UgycgUnxh_jjk_njBwZ4AaABAg",
        "write_date": "2019-11-12",
        "url": "https://www.youtube.com/channel/UCBkyj16n2snkRg1BAzpovXQ",
        "parent_url": "https://www.youtube.com/watch?v=hi9nDUwwYWc",
        "source_site": "https://www.youtube.com/"
      },
      {
        "content": "(비속어) 답답하넼",
        "writer": "UgxRAtOUPC3L4Jy3Cad4AaABAg",
        "write_date": "2019-11-12",
        "url": "https://www.youtube.com/channel/UCBkyj16n2snkRg1BAzpovXQ",
        "parent_url": "https://www.youtube.com/watch?v=hi9nDUwwYWc",
        "source_site": "https://www.youtube.com/"
      },
      {
        "content": "47분 채팅",
        "writer": "UgxYzZR-nr0Xb4qxJ0t4AaABAg",
        "write_date": "2019-11-12",
        "url": "https://www.youtube.com/channel/UCBkyj16n2snkRg1BAzpovXQ",
        "parent_url": "https://www.youtube.com/watch?v=hi9nDUwwYWc",
        "source_site": "https://www.youtube.com/"
      },
      {
        "content": "저만 끊기나요,",
        "writer": "Ugz_Q_l090if2Mzi2k14AaABAg",
        "write_date": "2019-11-12",
        "url": "https://www.youtube.com/channel/UCBkyj16n2snkRg1BAzpovXQ",
        "parent_url": "https://www.youtube.com/watch?v=hi9nDUwwYWc",
        "source_site": "https://www.youtube.com/"
      },
      {
        "content": "앜 이거 보고 구독합니다",
        "writer": "UgzapeTnOka96LTLwPl4AaABAg",
        "write_date": "2019-11-12",
        "url": "https://www.youtube.com/channel/UCBkyj16n2snkRg1BAzpovXQ",
        "parent_url": "https://www.youtube.com/watch?v=hi9nDUwwYWc",
        "source_site": "https://www.youtube.com/"
      },
      {
        "content": "게임 (비속어)나 참신하네",
        "writer": "UgzPSYz3qP5Z2cPFSfx4AaABAg",
        "write_date": "2019-11-12",
        "url": "https://www.youtube.com/channel/UCBkyj16n2snkRg1BAzpovXQ",
        "parent_url": "https://www.youtube.com/watch?v=hi9nDUwwYWc",
        "source_site": "https://www.youtube.com/"
      },
      {
        "content": "독창이랑 고양이랑 대화하는거봨",
        "writer": "UgzYQAOw1Gxyq6yttkp4AaABAg",
        "write_date": "2018-11-12",
        "url": "https://www.youtube.com/channel/UCBkyj16n2snkRg1BAzpovXQ",
        "parent_url": "https://www.youtube.com/watch?v=hi9nDUwwYWc",
        "source_site": "https://www.youtube.com/"
      },
      {
        "content": "이게 왜 이제 나와 형",
        "writer": "UgypaWnyKZPxpjedtiV4AaABAg",
        "write_date": "2018-11-12",
        "url": "https://www.youtube.com/channel/UCBkyj16n2snkRg1BAzpovXQ",
        "parent_url": "https://www.youtube.com/watch?v=hi9nDUwwYWc",
        "source_site": "https://www.youtube.com/"
      },
      {
        "content": "하이라이트 올라온거보고 다시 보러왔어 너모꼴잼이자너",
        "writer": "UgyaDsH7MKBJSZ3G_d14AaABAg",
        "write_date": "2018-11-12",
        "url": "https://www.youtube.com/channel/UCBkyj16n2snkRg1BAzpovXQ",
        "parent_url": "https://www.youtube.com/watch?v=hi9nDUwwYWc",
        "source_site": "https://www.youtube.com/"
      },
      {
        "content": "아 근데 생쥐 뒤통수치면 눈 튀어나올 것 같이 생겼네 개무서움",
        "writer": "Ugw2zwCRPeN9_VbdHkF4AaABAg",
        "write_date": "2018-11-12",
        "url": "https://www.youtube.com/channel/UCBkyj16n2snkRg1BAzpovXQ",
        "parent_url": "https://www.youtube.com/watch?v=hi9nDUwwYWc",
        "source_site": "https://www.youtube.com/"
      },
      {
        "content": "진짜 이거 겜스터 합방하면 졸잼일듯",
        "writer": "UgxyPDggMDiVe_tDvtR4AaABAg",
        "write_date": "2018-11-12",
        "url": "https://www.youtube.com/channel/UCBkyj16n2snkRg1BAzpovXQ",
        "parent_url": "https://www.youtube.com/watch?v=hi9nDUwwYWc",
        "source_site": "https://www.youtube.com/"
      },
      {
        "content": "이거 인원 설정을 많이 가능하면 겜스터 합방해도되겠다",
        "writer": "Ugwu5JJpfksV-FfEdRd4AaABAg",
        "write_date": "2018-11-12",
        "url": "https://www.youtube.com/channel/UCBkyj16n2snkRg1BAzpovXQ",
        "parent_url": "https://www.youtube.com/watch?v=hi9nDUwwYWc",
        "source_site": "https://www.youtube.com/"
      },
      {
        "content": "이게임 어떻게되었나요 패치나 바뀐게있나요 유료게임인가요",
        "writer": "UgxMRWdkhUIBVEkavhh4AaABAg",
        "write_date": "2018-11-12",
        "url": "https://www.youtube.com/channel/UCBkyj16n2snkRg1BAzpovXQ",
        "parent_url": "https://www.youtube.com/watch?v=hi9nDUwwYWc",
        "source_site": "https://www.youtube.com/"
      },
      {
        "content": "우엥 너므주탸",
        "writer": "Ugy8Dt3lx6hc5hi8xCN4AaABAg",
        "write_date": "2018-11-12",
        "url": "https://www.youtube.com/channel/UCBkyj16n2snkRg1BAzpovXQ",
        "parent_url": "https://www.youtube.com/watch?v=hi9nDUwwYWc",
        "source_site": "https://www.youtube.com/"
      },
      {
        "content": "햄스터본능 어디안가는 왁굳",
        "writer": "UgwCpX_Mb2sgohO1VoN4AaABAg",
        "write_date": "2018-11-12",
        "url": "https://www.youtube.com/channel/UCBkyj16n2snkRg1BAzpovXQ",
        "parent_url": "https://www.youtube.com/watch?v=hi9nDUwwYWc",
        "source_site": "https://www.youtube.com/"
      },
      {
        "content": "광고 꽈아악꽈아아악 넣은거보소",
        "writer": "Ugy6MNratPpz9VyUEFx4AaABAg",
        "write_date": "2018-11-12",
        "url": "https://www.youtube.com/channel/UCBkyj16n2snkRg1BAzpovXQ",
        "parent_url": "https://www.youtube.com/watch?v=hi9nDUwwYWc",
        "source_site": "https://www.youtube.com/"
      },
      {
        "content": "그의 현란한 춤",
        "writer": "UgwuSDuA-riO8WaDCkB4AaABAg",
        "write_date": "2018-11-12",
        "url": "https://www.youtube.com/channel/UCBkyj16n2snkRg1BAzpovXQ",
        "parent_url": "https://www.youtube.com/watch?v=hi9nDUwwYWc",
        "source_site": "https://www.youtube.com/"
      },
      {
        "content": "(비속어) 애인 장 1급",
        "writer": "UgzVQFyntWpnhFhONU14AaABAg",
        "write_date": "2018-11-12",
        "url": "https://www.youtube.com/channel/UCBkyj16n2snkRg1BAzpovXQ",
        "parent_url": "https://www.youtube.com/watch?v=hi9nDUwwYWc",
        "source_site": "https://www.youtube.com/"
      },
      {
        "content": "형 넘무 귀여오 .",
        "writer": "Ugx6HRsnV6IOd0puw1N4AaABAg",
        "write_date": "2018-11-12",
        "url": "https://www.youtube.com/channel/UCBkyj16n2snkRg1BAzpovXQ",
        "parent_url": "https://www.youtube.com/watch?v=hi9nDUwwYWc",
        "source_site": "https://www.youtube.com/"
      },
      {
        "content": "아니 관전이 (비속어) 물건을 건드릴수 있으면 어떻게햌",
        "writer": "Ugwp7Zn7p9r8gWa-Wbl4AaABAg",
        "write_date": "2018-11-12",
        "url": "https://www.youtube.com/channel/UCBkyj16n2snkRg1BAzpovXQ",
        "parent_url": "https://www.youtube.com/watch?v=hi9nDUwwYWc",
        "source_site": "https://www.youtube.com/"
      },
      {
        "content": "진심 천장 시야 개 (비속어)같다",
        "writer": "Ugz6HswWni2xo3AhyYF4AaABAg",
        "write_date": "2018-11-12",
        "url": "https://www.youtube.com/channel/UCBkyj16n2snkRg1BAzpovXQ",
        "parent_url": "https://www.youtube.com/watch?v=hi9nDUwwYWc",
        "source_site": "https://www.youtube.com/"
      },
      {
        "content": "이 영상은 그냥 전체적으로 형 너무 귀여운거같아 너무 좋아",
        "writer": "Ugxqjg_ouqTn74zcr-F4AaABAg",
        "write_date": "2018-11-12",
        "url": "https://www.youtube.com/channel/UCBkyj16n2snkRg1BAzpovXQ",
        "parent_url": "https://www.youtube.com/watch?v=hi9nDUwwYWc",
        "source_site": "https://www.youtube.com/"
      },
      {
        "content": "그대를 만나고",
        "writer": "UgwyjHwCPztp1la35eR4AaABAg",
        "write_date": "2018-11-12",
        "url": "https://www.youtube.com/channel/UCBkyj16n2snkRg1BAzpovXQ",
        "parent_url": "https://www.youtube.com/watch?v=hi9nDUwwYWc",
        "source_site": "https://www.youtube.com/"
      },
      {
        "content": "우리 애기들 할때 나만 설렘 헝헝 왁형 사랑해",
        "writer": "Ugz8u6Hvlke9I3DQ5sZ4AaABAg",
        "write_date": "2017-11-12",
        "url": "https://www.youtube.com/channel/UCBkyj16n2snkRg1BAzpovXQ",
        "parent_url": "https://www.youtube.com/watch?v=hi9nDUwwYWc",
        "source_site": "https://www.youtube.com/"
      },
      {
        "content": "최고로 재밌네요.",
        "writer": "Ugx91KD_WfGkhe6-3lp4AaABAg",
        "write_date": "2017-11-12",
        "url": "https://www.youtube.com/channel/UCBkyj16n2snkRg1BAzpovXQ",
        "parent_url": "https://www.youtube.com/watch?v=hi9nDUwwYWc",
        "source_site": "https://www.youtube.com/"
      },
      {
        "content": "초 뭔소리지",
        "writer": "Ugy0yf7aYN0ycl-GxJp4AaABAg",
        "write_date": "2017-11-12",
        "url": "https://www.youtube.com/channel/UCBkyj16n2snkRg1BAzpovXQ",
        "parent_url": "https://www.youtube.com/watch?v=hi9nDUwwYWc",
        "source_site": "https://www.youtube.com/"
      },
      {
        "content": "형 이거 한번만 더해줘 (비속어)잼",
        "writer": "UgwHCT4amEkokLpI9hx4AaABAg",
        "write_date": "2017-11-12",
        "url": "https://www.youtube.com/channel/UCBkyj16n2snkRg1BAzpovXQ",
        "parent_url": "https://www.youtube.com/watch?v=hi9nDUwwYWc",
        "source_site": "https://www.youtube.com/"
      },
      {
        "content": "토므과즈에리 야무지게 재미진 게임일까",
        "writer": "Ugh00QxQzxxXhngCoAEC",
        "write_date": "2017-11-12",
        "url": "https://www.youtube.com/channel/UCBkyj16n2snkRg1BAzpovXQ",
        "parent_url": "https://www.youtube.com/watch?v=hi9nDUwwYWc",
        "source_site": "https://www.youtube.com/"
      },
      {
        "content": "솔직히 이거 (비속어) 재밌게봤다, 이거 또해주셨으면진짜 1시간 개빨리 갔음",
        "writer": "UggzxevqolbwOngCoAEC",
        "write_date": "2017-11-12",
        "url": "https://www.youtube.com/channel/UCBkyj16n2snkRg1BAzpovXQ",
        "parent_url": "https://www.youtube.com/watch?v=hi9nDUwwYWc",
        "source_site": "https://www.youtube.com/"
      },
      {
        "content": "(반사회적용어) 배찢어지는줄 알았네",
        "writer": "UggNdpChomnkIHgCoAEC",
        "write_date": "2017-11-12",
        "url": "https://www.youtube.com/channel/UCBkyj16n2snkRg1BAzpovXQ",
        "parent_url": "https://www.youtube.com/watch?v=hi9nDUwwYWc",
        "source_site": "https://www.youtube.com/"
      },
      {
        "content": "쿠소치고는 꽤 괜찮은거같군요. 번역이나 여러가지 손좀 보면 충분히 사람모을수있을듯",
        "writer": "Ugg6lLRn2-LMGHgCoAEC",
        "write_date": "2017-11-12",
        "url": "https://www.youtube.com/channel/UCBkyj16n2snkRg1BAzpovXQ",
        "parent_url": "https://www.youtube.com/watch?v=hi9nDUwwYWc",
        "source_site": "https://www.youtube.com/"
      },
      {
        "content": "형 이거 게임이 GTA5로 되어있어. 확인해조 찡긋.",
        "writer": "Ugg2XN5IFz9mRngCoAEC",
        "write_date": "2017-11-12",
        "url": "https://www.youtube.com/channel/UCBkyj16n2snkRg1BAzpovXQ",
        "parent_url": "https://www.youtube.com/watch?v=hi9nDUwwYWc",
        "source_site": "https://www.youtube.com/"
      },
      {
        "content": "역시 쿠소겜이 젤 웃겨 쉬밬",
        "writer": "Ugh3Wwtx_Bp9VngCoAEC",
        "write_date": "2017-11-12",
        "url": "https://www.youtube.com/channel/UCBkyj16n2snkRg1BAzpovXQ",
        "parent_url": "https://www.youtube.com/watch?v=hi9nDUwwYWc",
        "source_site": "https://www.youtube.com/"
      },
      {
        "content": "레알 청자들 센스 좋았네",
        "writer": "Ugi7vFalPEb-UXgCoAEC",
        "write_date": "2017-11-12",
        "url": "https://www.youtube.com/channel/UCBkyj16n2snkRg1BAzpovXQ",
        "parent_url": "https://www.youtube.com/watch?v=hi9nDUwwYWc",
        "source_site": "https://www.youtube.com/"
      },
      {
        "content": "킬링파트 우울할때봐야지",
        "writer": "Ugg0mgjx76RtgngCoAEC",
        "write_date": "2017-11-12",
        "url": "https://www.youtube.com/channel/UCBkyj16n2snkRg1BAzpovXQ",
        "parent_url": "https://www.youtube.com/watch?v=hi9nDUwwYWc",
        "source_site": "https://www.youtube.com/"
      },
      {
        "content": "진짜 겜 개대충만들었네",
        "writer": "UgiAnBM24DMLaHgCoAEC",
        "write_date": "2017-11-12",
        "url": "https://www.youtube.com/channel/UCBkyj16n2snkRg1BAzpovXQ",
        "parent_url": "https://www.youtube.com/watch?v=hi9nDUwwYWc",
        "source_site": "https://www.youtube.com/"
      },
      {
        "content": "형 광고 너무 많아서 그켬이야",
        "writer": "Ugie-PsWgASkhXgCoAEC",
        "write_date": "2017-11-12",
        "url": "https://www.youtube.com/channel/UCBkyj16n2snkRg1BAzpovXQ",
        "parent_url": "https://www.youtube.com/watch?v=hi9nDUwwYWc",
        "source_site": "https://www.youtube.com/"
      },
      {
        "content": "뭐 결국 왁인마잖아",
        "writer": "UgjB45uzAAl08ngCoAEC",
        "write_date": "2017-11-12",
        "url": "https://www.youtube.com/channel/UCBkyj16n2snkRg1BAzpovXQ",
        "parent_url": "https://www.youtube.com/watch?v=hi9nDUwwYWc",
        "source_site": "https://www.youtube.com/"
      },
      {
        "content": "독창 부성애",
        "writer": "UghkQHiR_uzRjHgCoAEC",
        "write_date": "2017-11-12",
        "url": "https://www.youtube.com/channel/UCBkyj16n2snkRg1BAzpovXQ",
        "parent_url": "https://www.youtube.com/watch?v=hi9nDUwwYWc",
        "source_site": "https://www.youtube.com/"
      },
      {
        "content": "아 순간 왁굳채널 아닌줄 알았어 썸네일 너무 큗으하다",
        "writer": "UggubaCPvJNo03gCoAEC",
        "write_date": "2017-11-12",
        "url": "https://www.youtube.com/channel/UCBkyj16n2snkRg1BAzpovXQ",
        "parent_url": "https://www.youtube.com/watch?v=hi9nDUwwYWc",
        "source_site": "https://www.youtube.com/"
      },
      {
        "content": "오빠 생일 축하해",
        "writer": "UghW_LHP_j4vK3gCoAEC",
        "write_date": "2017-11-12",
        "url": "https://www.youtube.com/channel/UCBkyj16n2snkRg1BAzpovXQ",
        "parent_url": "https://www.youtube.com/watch?v=hi9nDUwwYWc",
        "source_site": "https://www.youtube.com/"
      },
      {
        "content": "차가 드로리언",
        "writer": "UgiLOytVLfDNgXgCoAEC",
        "write_date": "2017-11-12",
        "url": "https://www.youtube.com/channel/UCBkyj16n2snkRg1BAzpovXQ",
        "parent_url": "https://www.youtube.com/watch?v=hi9nDUwwYWc",
        "source_site": "https://www.youtube.com/"
      },
      {
        "content": "애기들 귀엽닼 눈물나는 부성애여",
        "writer": "Uggjwid7zY3EFHgCoAEC",
        "write_date": "2017-11-12",
        "url": "https://www.youtube.com/channel/UCBkyj16n2snkRg1BAzpovXQ",
        "parent_url": "https://www.youtube.com/watch?v=hi9nDUwwYWc",
        "source_site": "https://www.youtube.com/"
      },
      {
        "content": "기억 지우고 다시 계속 보고 싶다 너무 좋아 (반사회적용어)텽",
        "writer": "UghZFKpH2NakvXgCoAEC",
        "write_date": "2017-11-12",
        "url": "https://www.youtube.com/channel/UCBkyj16n2snkRg1BAzpovXQ",
        "parent_url": "https://www.youtube.com/watch?v=hi9nDUwwYWc",
        "source_site": "https://www.youtube.com/"
      },
      {
        "content": "역시 햄스터출(이름) 쥐(비속어)할 때 잘하네",
        "writer": "UgguZ9(반사회적용어)YHk5cHgCoAEC",
        "write_date": "2017-11-12",
        "url": "https://www.youtube.com/channel/UCBkyj16n2snkRg1BAzpovXQ",
        "parent_url": "https://www.youtube.com/watch?v=hi9nDUwwYWc",
        "source_site": "https://www.youtube.com/"
      },
      {
        "content": "근데 왜 갑자기 10분 편집 이런거 안올라와요 편집자 결국 관뒀나요",
        "writer": "Ugh5-XXpzlps2XgCoAEC",
        "write_date": "2017-11-12",
        "url": "https://www.youtube.com/channel/UCBkyj16n2snkRg1BAzpovXQ",
        "parent_url": "https://www.youtube.com/watch?v=hi9nDUwwYWc",
        "source_site": "https://www.youtube.com/"
      },
      {
        "content": "유작이 제대로 살리네",
        "writer": "Ugh8oBM9N-pp8HgCoAEC",
        "write_date": "2017-11-12",
        "url": "https://www.youtube.com/channel/UCBkyj16n2snkRg1BAzpovXQ",
        "parent_url": "https://www.youtube.com/watch?v=hi9nDUwwYWc",
        "source_site": "https://www.youtube.com/"
      },
      {
        "content": "우리애기들 심쿵,",
        "writer": "UghbFe1gne_niHgCoAEC",
        "write_date": "2017-11-12",
        "url": "https://www.youtube.com/channel/UCBkyj16n2snkRg1BAzpovXQ",
        "parent_url": "https://www.youtube.com/watch?v=hi9nDUwwYWc",
        "source_site": "https://www.youtube.com/"
      },
      {
        "content": "(반사회적용어)때 당시 3D 게임의 신세계를 처음 맛보게 해준 리볼트와 비슷한 느낌이 들어서 너무 좋다 쿠소의 신세계",
        "writer": "Ugirw5DMN1_NjXgCoAEC",
        "write_date": "2017-11-12",
        "url": "https://www.youtube.com/channel/UCBkyj16n2snkRg1BAzpovXQ",
        "parent_url": "https://www.youtube.com/watch?v=hi9nDUwwYWc",
        "source_site": "https://www.youtube.com/"
      },
      {
        "content": "왁굳형, GTA5가 그리워요,",
        "writer": "Ugg6BbzLKn4Dl3gCoAEC",
        "write_date": "2017-11-12",
        "url": "https://www.youtube.com/channel/UCBkyj16n2snkRg1BAzpovXQ",
        "parent_url": "https://www.youtube.com/watch?v=hi9nDUwwYWc",
        "source_site": "https://www.youtube.com/"
      },
      {
        "content": "근데 솔직히 암걸렸어 형",
        "writer": "UghkQqACPdBnZXgCoAEC",
        "write_date": "2017-11-12",
        "url": "https://www.youtube.com/channel/UCBkyj16n2snkRg1BAzpovXQ",
        "parent_url": "https://www.youtube.com/watch?v=hi9nDUwwYWc",
        "source_site": "https://www.youtube.com/"
      },
      {
        "content": "처음에 트위치애들이 유하 유하 거리는거 너무 귀여운것 같아,",
        "writer": "Ugjv43lV4mgNQ3gCoAEC",
        "write_date": "2017-11-12",
        "url": "https://www.youtube.com/channel/UCBkyj16n2snkRg1BAzpovXQ",
        "parent_url": "https://www.youtube.com/watch?v=hi9nDUwwYWc",
        "source_site": "https://www.youtube.com/"
      },
      {
        "content": "2층은 못 올라 가나.",
        "writer": "UgiOe_PK_wsDTHgCoAEC",
        "write_date": "2017-11-12",
        "url": "https://www.youtube.com/channel/UCBkyj16n2snkRg1BAzpovXQ",
        "parent_url": "https://www.youtube.com/watch?v=hi9nDUwwYWc",
        "source_site": "https://www.youtube.com/"
      },
      {
        "content": "49 (비속어)(비속어)웃곀",
        "writer": "UgjoYvxVfYkPyHgCoAEC",
        "write_date": "2017-11-12",
        "url": "https://www.youtube.com/channel/UCBkyj16n2snkRg1BAzpovXQ",
        "parent_url": "https://www.youtube.com/watch?v=hi9nDUwwYWc",
        "source_site": "https://www.youtube.com/"
      },
      {
        "content": "아기가 죽었습니다 뜨자마자 형은 좋은 아(비속어) 될것같앜",
        "writer": "UgjWLNXoplI7E3gCoAEC",
        "write_date": "2017-11-12",
        "url": "https://www.youtube.com/channel/UCBkyj16n2snkRg1BAzpovXQ",
        "parent_url": "https://www.youtube.com/watch?v=hi9nDUwwYWc",
        "source_site": "https://www.youtube.com/"
      },
      {
        "content": "영원한 길치",
        "writer": "UgizM5VT_LKm0ngCoAEC",
        "write_date": "2017-11-12",
        "url": "https://www.youtube.com/channel/UCBkyj16n2snkRg1BAzpovXQ",
        "parent_url": "https://www.youtube.com/watch?v=hi9nDUwwYWc",
        "source_site": "https://www.youtube.com/"
      },
      {
        "content": "오 별기대 없이 봤는데 레알 잼따",
        "writer": "UgixdeyF3CIyoHgCoAEC",
        "write_date": "2017-11-12",
        "url": "https://www.youtube.com/channel/UCBkyj16n2snkRg1BAzpovXQ",
        "parent_url": "https://www.youtube.com/watch?v=hi9nDUwwYWc",
        "source_site": "https://www.youtube.com/"
      },
      {
        "content": "나만 광고 안봤냐",
        "writer": "Uggq6ojI_k5A0XgCoAEC",
        "write_date": "2017-11-12",
        "url": "https://www.youtube.com/channel/UCBkyj16n2snkRg1BAzpovXQ",
        "parent_url": "https://www.youtube.com/watch?v=hi9nDUwwYWc",
        "source_site": "https://www.youtube.com/"
      },
      {
        "content": "날파산무커 조회수안나와서 관",
        "writer": "Ugh5-XXpzlps2XgCoAEC.8VN3t0vL-E88VNC5CQESYZ",
        "write_date": "2017-11-12",
        "url": "https://www.youtube.com/channel/UCBkyj16n2snkRg1BAzpovXQ",
        "parent_url": "https://www.youtube.com/watch?v=hi9nDUwwYWc",
        "source_site": "https://www.youtube.com/"
      },
      {
        "content": "(반사회적용어) 이게뭐여",
        "writer": "UgiIuFgZQP-sCngCoAEC.8VMp7QAnF508Vg9ey1f6gn",
        "write_date": "2017-11-12",
        "url": "https://www.youtube.com/channel/UCBkyj16n2snkRg1BAzpovXQ",
        "parent_url": "https://www.youtube.com/watch?v=hi9nDUwwYWc",
        "source_site": "https://www.youtube.com/"
      },
      {
        "content": "왁굳형 엉덩이 내꺼 (비속어),",
        "writer": "UgiIuFgZQP-sCngCoAEC.8VMp7QAnF509DPmSGCNUco",
        "write_date": "2020-11-12",
        "url": "https://www.youtube.com/channel/UCBkyj16n2snkRg1BAzpovXQ",
        "parent_url": "https://www.youtube.com/watch?v=hi9nDUwwYWc",
        "source_site": "https://www.youtube.com/"
      },
      {
        "content": "왁주니어 상상도 안간다.",
        "writer": "UgjWLNXoplI7E3gCoAEC.8VMcmpl5QR297sW8l2V3_U",
        "write_date": "2020-11-12",
        "url": "https://www.youtube.com/channel/UCBkyj16n2snkRg1BAzpovXQ",
        "parent_url": "https://www.youtube.com/watch?v=hi9nDUwwYWc",
        "source_site": "https://www.youtube.com/"
      },
      {
        "content": "오랜만에 덜 쿠소게임이네",
        "writer": "Ughl-k1jYHaT-ngCoAEC",
        "write_date": "2017-11-12",
        "url": "https://www.youtube.com/channel/UCBkyj16n2snkRg1BAzpovXQ",
        "parent_url": "https://www.youtube.com/watch?v=hi9nDUwwYWc",
        "source_site": "https://www.youtube.com/"
      },
      {
        "content": "이거 존잼이야 담에 또 해줘 형",
        "writer": "UghsTYl8AOXqiXgCoAEC",
        "write_date": "2017-11-12",
        "url": "https://www.youtube.com/channel/UCBkyj16n2snkRg1BAzpovXQ",
        "parent_url": "https://www.youtube.com/watch?v=hi9nDUwwYWc",
        "source_site": "https://www.youtube.com/"
      },
      {
        "content": "(비속어)잼 나도 이거보고 이게임 삼",
        "writer": "Ugi82Sk4tYRENngCoAEC",
        "write_date": "2017-11-12",
        "url": "https://www.youtube.com/channel/UCBkyj16n2snkRg1BAzpovXQ",
        "parent_url": "https://www.youtube.com/watch?v=hi9nDUwwYWc",
        "source_site": "https://www.youtube.com/"
      },
      {
        "content": "형 다른맵은 없었어",
        "writer": "UghdfF7QvTtEcXgCoAEC",
        "write_date": "2017-11-12",
        "url": "https://www.youtube.com/channel/UCBkyj16n2snkRg1BAzpovXQ",
        "parent_url": "https://www.youtube.com/watch?v=hi9nDUwwYWc",
        "source_site": "https://www.youtube.com/"
      },
      {
        "content": "와 진짜 왁굳형 더럽게 못하냐",
        "writer": "UgjI6AlRtATulXgCoAEC",
        "write_date": "2017-11-12",
        "url": "https://www.youtube.com/channel/UCBkyj16n2snkRg1BAzpovXQ",
        "parent_url": "https://www.youtube.com/watch?v=hi9nDUwwYWc",
        "source_site": "https://www.youtube.com/"
      },
      {
        "content": "이렇게 긴영상 너무 좋아요 앞으로도 자주 올려주세요",
        "writer": "Ugg2JlSITuR9xngCoAEC",
        "write_date": "2017-11-12",
        "url": "https://www.youtube.com/channel/UCBkyj16n2snkRg1BAzpovXQ",
        "parent_url": "https://www.youtube.com/watch?v=hi9nDUwwYWc",
        "source_site": "https://www.youtube.com/"
      },
      {
        "content": "형 실버버튼은 어떻게 되는거야",
        "writer": "UghJg-x2lJBvF3gCoAEC",
        "write_date": "2017-11-12",
        "url": "https://www.youtube.com/channel/UCBkyj16n2snkRg1BAzpovXQ",
        "parent_url": "https://www.youtube.com/watch?v=hi9nDUwwYWc",
        "source_site": "https://www.youtube.com/"
      },
      {
        "content": "개 그래픽 (혐오표현) 동물경기급 쿠소 (비속어)(비속어)인줄 알았는데 첨에 튜토리얼보고 좀 놀랐다",
        "writer": "UgjY2X3a091pgHgCoAEC",
        "write_date": "2017-11-12",
        "url": "https://www.youtube.com/channel/UCBkyj16n2snkRg1BAzpovXQ",
        "parent_url": "https://www.youtube.com/watch?v=hi9nDUwwYWc",
        "source_site": "https://www.youtube.com/"
      },
      {
        "content": "고양이 여깄으니까 애들부터 먹여 진정 아빠맘, 설렜다",
        "writer": "UggZvUCoKoMWrngCoAEC",
        "write_date": "2017-11-12",
        "url": "https://www.youtube.com/channel/UCBkyj16n2snkRg1BAzpovXQ",
        "parent_url": "https://www.youtube.com/watch?v=hi9nDUwwYWc",
        "source_site": "https://www.youtube.com/"
      },
      {
        "content": "형 나 요새 형 방송 꼭 챙겨보고 좋아요도 다 눌렀어 앙 왁창띠",
        "writer": "Ugi7flXKhW3OMngCoAEC",
        "write_date": "2017-11-12",
        "url": "https://www.youtube.com/channel/UCBkyj16n2snkRg1BAzpovXQ",
        "parent_url": "https://www.youtube.com/watch?v=hi9nDUwwYWc",
        "source_site": "https://www.youtube.com/"
      },
      {
        "content": "겜스터 합방각",
        "writer": "Ugia-_31x8c333gCoAEC",
        "write_date": "2017-11-12",
        "url": "https://www.youtube.com/channel/UCBkyj16n2snkRg1BAzpovXQ",
        "parent_url": "https://www.youtube.com/watch?v=hi9nDUwwYWc",
        "source_site": "https://www.youtube.com/"
      },
      {
        "content": "형 광고수 너무 한거 아니야 다 보기 힘들어",
        "writer": "UgjaWfFAC2RUongCoAEC",
        "write_date": "2017-11-12",
        "url": "https://www.youtube.com/channel/UCBkyj16n2snkRg1BAzpovXQ",
        "parent_url": "https://www.youtube.com/watch?v=hi9nDUwwYWc",
        "source_site": "https://www.youtube.com/"
      },
      {
        "content": "형 간석동 침수됐다던데 괜찮아 늙어서 못 빠져나오는거 아니지",
        "writer": "UghjFt_BROBja3gCoAEC",
        "write_date": "2017-11-12",
        "url": "https://www.youtube.com/channel/UCBkyj16n2snkRg1BAzpovXQ",
        "parent_url": "https://www.youtube.com/watch?v=hi9nDUwwYWc",
        "source_site": "https://www.youtube.com/"
      },
      {
        "content": "오쨩비명 기머리이이",
        "writer": "UghBlwgszdti-HgCoAEC",
        "write_date": "2017-11-12",
        "url": "https://www.youtube.com/channel/UCBkyj16n2snkRg1BAzpovXQ",
        "parent_url": "https://www.youtube.com/watch?v=hi9nDUwwYWc",
        "source_site": "https://www.youtube.com/"
      },
      {
        "content": "저 날라다니는 새들도 탈수있나",
        "writer": "UggN7vQRPWoiUngCoAEC",
        "write_date": "2017-11-12",
        "url": "https://www.youtube.com/channel/UCBkyj16n2snkRg1BAzpovXQ",
        "parent_url": "https://www.youtube.com/watch?v=hi9nDUwwYWc",
        "source_site": "https://www.youtube.com/"
      },
      {
        "content": "깐족거리는거 개웃기넼",
        "writer": "UghNVn89y7NiuHgCoAEC",
        "write_date": "2017-11-12",
        "url": "https://www.youtube.com/channel/UCBkyj16n2snkRg1BAzpovXQ",
        "parent_url": "https://www.youtube.com/watch?v=hi9nDUwwYWc",
        "source_site": "https://www.youtube.com/"
      },
      {
        "content": "형 간석역 물에 잠겼다는데 걱정되네 (비속어)왁말고 우리메씨",
        "writer": "UgihtMVNptfoYngCoAEC",
        "write_date": "2017-11-12",
        "url": "https://www.youtube.com/channel/UCBkyj16n2snkRg1BAzpovXQ",
        "parent_url": "https://www.youtube.com/watch?v=hi9nDUwwYWc",
        "source_site": "https://www.youtube.com/"
      },
      {
        "content": "좀 볼라하면 광고나오네 어이 형씨 너무한거 아니오",
        "writer": "Ugh_NdBR_r3dSngCoAEC",
        "write_date": "2017-11-12",
        "url": "https://www.youtube.com/channel/UCBkyj16n2snkRg1BAzpovXQ",
        "parent_url": "https://www.youtube.com/watch?v=hi9nDUwwYWc",
        "source_site": "https://www.youtube.com/"
      },
      {
        "content": "요즘 (이름) 프로필이 너무 유아채널같아요",
        "writer": "UgjK7FeqHzKJEXgCoAEC",
        "write_date": "2017-11-12",
        "url": "https://www.youtube.com/channel/UCBkyj16n2snkRg1BAzpovXQ",
        "parent_url": "https://www.youtube.com/watch?v=hi9nDUwwYWc",
        "source_site": "https://www.youtube.com/"
      },
      {
        "content": "(이름) 관",
        "writer": "UghJg-x2lJBvF3gCoAEC.8VLsDhsMq2z8VPWxHYf1Dt",
        "write_date": "2017-11-12",
        "url": "https://www.youtube.com/channel/UCBkyj16n2snkRg1BAzpovXQ",
        "parent_url": "https://www.youtube.com/watch?v=hi9nDUwwYWc",
        "source_site": "https://www.youtube.com/"
      },
      {
        "content": "관 한글자 달아 놓은거 (비속어)웃기네 한글자에 함축된 의미 무엇",
        "writer": "UghJg-x2lJBvF3gCoAEC.8VLsDhsMq2z8a-Ewv1ZyWx",
        "write_date": "2018-11-12",
        "url": "https://www.youtube.com/channel/UCBkyj16n2snkRg1BAzpovXQ",
        "parent_url": "https://www.youtube.com/watch?v=hi9nDUwwYWc",
        "source_site": "https://www.youtube.com/"
      },
      {
        "content": "장글 두칠님이랑 (이름)도 (이름)처럼 바뀜",
        "writer": "UgjK7FeqHzKJEXgCoAEC.8VLIjQuRV-X8VLab_uHF2k",
        "write_date": "2017-11-12",
        "url": "https://www.youtube.com/channel/UCBkyj16n2snkRg1BAzpovXQ",
        "parent_url": "https://www.youtube.com/watch?v=hi9nDUwwYWc",
        "source_site": "https://www.youtube.com/"
      },
      {
        "content": "유아채널이 되고 싶은 서른 왁두 입니다",
        "writer": "UgjK7FeqHzKJEXgCoAEC.8VLIjQuRV-X8VLh40ZipuG",
        "write_date": "2017-11-12",
        "url": "https://www.youtube.com/channel/UCBkyj16n2snkRg1BAzpovXQ",
        "parent_url": "https://www.youtube.com/watch?v=hi9nDUwwYWc",
        "source_site": "https://www.youtube.com/"
      },
      {
        "content": "장글 2030대 사람들 사로잡고이제 영유아기 친구들까지접수하려는 엄청난 전략이죠",
        "writer": "UgjK7FeqHzKJEXgCoAEC.8VLIjQuRV-X8VLhVAOvE6b",
        "write_date": "2017-11-12",
        "url": "https://www.youtube.com/channel/UCBkyj16n2snkRg1BAzpovXQ",
        "parent_url": "https://www.youtube.com/watch?v=hi9nDUwwYWc",
        "source_site": "https://www.youtube.com/"
      },
      {
        "content": "병현 영유아깈영유아기는 심햇닼",
        "writer": "UgjK7FeqHzKJEXgCoAEC.8VLIjQuRV-X8VMLDQ95o58",
        "write_date": "2017-11-12",
        "url": "https://www.youtube.com/channel/UCBkyj16n2snkRg1BAzpovXQ",
        "parent_url": "https://www.youtube.com/watch?v=hi9nDUwwYWc",
        "source_site": "https://www.youtube.com/"
      },
      {
        "content": "여러 개의 팬아트 중에 겜스터 멤버들이 투표로 정해 1위로 선정된거라 겜스터 멤버들 프사 다 요겁니다",
        "writer": "UgjK7FeqHzKJEXgCoAEC.8VLIjQuRV-X8VMfjGG1Ui3",
        "write_date": "2017-11-12",
        "url": "https://www.youtube.com/channel/UCBkyj16n2snkRg1BAzpovXQ",
        "parent_url": "https://www.youtube.com/watch?v=hi9nDUwwYWc",
        "source_site": "https://www.youtube.com/"
      },
      {
        "content": "이제 왁창주니어 생기는거야",
        "writer": "UgjK7FeqHzKJEXgCoAEC.8VLIjQuRV-X8iZhgMki49D",
        "write_date": "2018-11-12",
        "url": "https://www.youtube.com/channel/UCBkyj16n2snkRg1BAzpovXQ",
        "parent_url": "https://www.youtube.com/watch?v=hi9nDUwwYWc",
        "source_site": "https://www.youtube.com/"
      },
      {
        "content": "시대 가 앞서간 게임",
        "writer": "UghjBI94E25BuXgCoAEC",
        "write_date": "2017-11-12",
        "url": "https://www.youtube.com/channel/UCBkyj16n2snkRg1BAzpovXQ",
        "parent_url": "https://www.youtube.com/watch?v=hi9nDUwwYWc",
        "source_site": "https://www.youtube.com/"
      },
      {
        "content": "(반사회적용어)텽 너무 쪼앗",
        "writer": "UghRvCbQygwXH3gCoAEC",
        "write_date": "2017-11-12",
        "url": "https://www.youtube.com/channel/UCBkyj16n2snkRg1BAzpovXQ",
        "parent_url": "https://www.youtube.com/watch?v=hi9nDUwwYWc",
        "source_site": "https://www.youtube.com/"
      },
      {
        "content": "왁형 미리생축",
        "writer": "Ugj1m9xhEbK6VHgCoAEC",
        "write_date": "2017-11-12",
        "url": "https://www.youtube.com/channel/UCBkyj16n2snkRg1BAzpovXQ",
        "parent_url": "https://www.youtube.com/watch?v=hi9nDUwwYWc",
        "source_site": "https://www.youtube.com/"
      },
      {
        "content": "형 어제 밤부터 틀어놓고 자고 틀어놓고 자고 세번이나 쭉 틀었어 칭찬해줘",
        "writer": "UgjiiuHjuYgHWXgCoAEC",
        "write_date": "2017-11-12",
        "url": "https://www.youtube.com/channel/UCBkyj16n2snkRg1BAzpovXQ",
        "parent_url": "https://www.youtube.com/watch?v=hi9nDUwwYWc",
        "source_site": "https://www.youtube.com/"
      },
      {
        "content": "형 치매야",
        "writer": "Ugj_zKOT0BBuKXgCoAEC",
        "write_date": "2017-11-12",
        "url": "https://www.youtube.com/channel/UCBkyj16n2snkRg1BAzpovXQ",
        "parent_url": "https://www.youtube.com/watch?v=hi9nDUwwYWc",
        "source_site": "https://www.youtube.com/"
      },
      {
        "content": "광고 겁나많네여",
        "writer": "Ugims591IAYHkngCoAEC",
        "write_date": "2017-11-12",
        "url": "https://www.youtube.com/channel/UCBkyj16n2snkRg1BAzpovXQ",
        "parent_url": "https://www.youtube.com/watch?v=hi9nDUwwYWc",
        "source_site": "https://www.youtube.com/"
      },
      {
        "content": "애들부터 먹여 왁버지 그는 대체",
        "writer": "UggCnZEPPNmqtngCoAEC",
        "write_date": "2017-11-12",
        "url": "https://www.youtube.com/channel/UCBkyj16n2snkRg1BAzpovXQ",
        "parent_url": "https://www.youtube.com/watch?v=hi9nDUwwYWc",
        "source_site": "https://www.youtube.com/"
      },
      {
        "content": "킹갓겜 이거 볼려고 고민하지말고 (비속어)보셈 왁두 요즘영상중에서 제일재밌는듯",
        "writer": "Ugg2CAb9yu0HCngCoAEC",
        "write_date": "2017-11-12",
        "url": "https://www.youtube.com/channel/UCBkyj16n2snkRg1BAzpovXQ",
        "parent_url": "https://www.youtube.com/watch?v=hi9nDUwwYWc",
        "source_site": "https://www.youtube.com/"
      },
      {
        "content": "원조 제리의 등판",
        "writer": "UgiMTTkmgK5MSXgCoAEC",
        "write_date": "2017-11-12",
        "url": "https://www.youtube.com/channel/UCBkyj16n2snkRg1BAzpovXQ",
        "parent_url": "https://www.youtube.com/watch?v=hi9nDUwwYWc",
        "source_site": "https://www.youtube.com/"
      },
      {
        "content": "당구대 안에 들어가서 아늑하다고 말하는데 우리형 귀여워,",
        "writer": "UggrROa_h_TiR3gCoAEC",
        "write_date": "2017-11-12",
        "url": "https://www.youtube.com/channel/UCBkyj16n2snkRg1BAzpovXQ",
        "parent_url": "https://www.youtube.com/watch?v=hi9nDUwwYWc",
        "source_site": "https://www.youtube.com/"
      },
      {
        "content": "형 신난거 너무 귀여워",
        "writer": "Uggk2l9WQX4pZngCoAEC",
        "write_date": "2017-11-12",
        "url": "https://www.youtube.com/channel/UCBkyj16n2snkRg1BAzpovXQ",
        "parent_url": "https://www.youtube.com/watch?v=hi9nDUwwYWc",
        "source_site": "https://www.youtube.com/"
      },
      {
        "content": "하 고치고 고치고 고치고 광고좀 그만보고싶다",
        "writer": "UgiGUt07oI32LXgCoAEC",
        "write_date": "2017-11-12",
        "url": "https://www.youtube.com/channel/UCBkyj16n2snkRg1BAzpovXQ",
        "parent_url": "https://www.youtube.com/watch?v=hi9nDUwwYWc",
        "source_site": "https://www.youtube.com/"
      },
      {
        "content": "한시간 15분 짜리 영상에 광고를 몇개나 넣은거야, (이름) 자낳괴 (반사회적용어)텽 사랑해,",
        "writer": "UghcGJdLO6HPhHgCoAEC",
        "write_date": "2017-11-12",
        "url": "https://www.youtube.com/channel/UCBkyj16n2snkRg1BAzpovXQ",
        "parent_url": "https://www.youtube.com/watch?v=hi9nDUwwYWc",
        "source_site": "https://www.youtube.com/"
      },
      {
        "content": "오쨩 너무 (반사회적용어)야.",
        "writer": "Uggxs9GvH0mWnXgCoAEC",
        "write_date": "2017-11-12",
        "url": "https://www.youtube.com/channel/UCBkyj16n2snkRg1BAzpovXQ",
        "parent_url": "https://www.youtube.com/watch?v=hi9nDUwwYWc",
        "source_site": "https://www.youtube.com/"
      },
      {
        "content": "(비속어)잼 그대를만나고호",
        "writer": "UgglD_LXUKbDvHgCoAEC",
        "write_date": "2017-11-12",
        "url": "https://www.youtube.com/channel/UCBkyj16n2snkRg1BAzpovXQ",
        "parent_url": "https://www.youtube.com/watch?v=hi9nDUwwYWc",
        "source_site": "https://www.youtube.com/"
      },
      {
        "content": "bgm이 없으니까 좀 심심하당. 그래도 게임 (비속어)잼",
        "writer": "UghayJI4pWDaKngCoAEC",
        "write_date": "2017-11-12",
        "url": "https://www.youtube.com/channel/UCBkyj16n2snkRg1BAzpovXQ",
        "parent_url": "https://www.youtube.com/watch?v=hi9nDUwwYWc",
        "source_site": "https://www.youtube.com/"
      },
      {
        "content": "(비속어) 웃기네",
        "writer": "UgjtAop7u54cP3gCoAEC",
        "write_date": "2017-11-12",
        "url": "https://www.youtube.com/channel/UCBkyj16n2snkRg1BAzpovXQ",
        "parent_url": "https://www.youtube.com/watch?v=hi9nDUwwYWc",
        "source_site": "https://www.youtube.com/"
      },
      {
        "content": "그냥 노잼이네요 비추드립니다",
        "writer": "Ugg93oUEvoOW53gCoAEC",
        "write_date": "2017-11-12",
        "url": "https://www.youtube.com/channel/UCBkyj16n2snkRg1BAzpovXQ",
        "parent_url": "https://www.youtube.com/watch?v=hi9nDUwwYWc",
        "source_site": "https://www.youtube.com/"
      },
      {
        "content": "진심으로 이 게임 관리와 업데이트만 잘해주면 대박일텐데 인원 늘려도 재미있을거 같고 맵도 새로운거 더 많이 아이템도 여러가지 ,그만큼 이 게임 홍보 많이하고 플레이 할테니. 우(이름) 덕에 잘 알게 되었고 잘 봤습니다",
        "writer": "UghZtPGKxxYuYHgCoAEC",
        "write_date": "2017-11-12",
        "url": "https://www.youtube.com/channel/UCBkyj16n2snkRg1BAzpovXQ",
        "parent_url": "https://www.youtube.com/watch?v=hi9nDUwwYWc",
        "source_site": "https://www.youtube.com/"
      },
      {
        "content": "꾸꾸까까 그냥 뒤쳐진거네, 근데 이건 나름 꿀잼이었어요. 우리는 무릎전철기 콜라보 아닌걸로도 좋아해야해요",
        "writer": "UghjBI94E25BuXgCoAEC.8VLHGtSUEay8XjbKYd5C5j",
        "write_date": "2017-11-12",
        "url": "https://www.youtube.com/channel/UCBkyj16n2snkRg1BAzpovXQ",
        "parent_url": "https://www.youtube.com/watch?v=hi9nDUwwYWc",
        "source_site": "https://www.youtube.com/"
      },
      {
        "content": "viollet 장소",
        "writer": "UghjBI94E25BuXgCoAEC.8VLHGtSUEay8iZhYkDw1WY",
        "write_date": "2018-11-12",
        "url": "https://www.youtube.com/channel/UCBkyj16n2snkRg1BAzpovXQ",
        "parent_url": "https://www.youtube.com/watch?v=hi9nDUwwYWc",
        "source_site": "https://www.youtube.com/"
      },
      {
        "content": "Peace Yang 억으로 장린",
        "writer": "UgiMTTkmgK5MSXgCoAEC.8VKnv7L8QEP8VLbUgk64B9",
        "write_date": "2017-11-12",
        "url": "https://www.youtube.com/channel/UCBkyj16n2snkRg1BAzpovXQ",
        "parent_url": "https://www.youtube.com/watch?v=hi9nDUwwYWc",
        "source_site": "https://www.youtube.com/"
      },
      {
        "content": "손수민 오늘도 외칩니다 흑흑 왁굳형 너무좋아",
        "writer": "Uggk2l9WQX4pZngCoAEC.8VKkiwUeJC98VLIkwWAvzN",
        "write_date": "2017-11-12",
        "url": "https://www.youtube.com/channel/UCBkyj16n2snkRg1BAzpovXQ",
        "parent_url": "https://www.youtube.com/watch?v=hi9nDUwwYWc",
        "source_site": "https://www.youtube.com/"
      },
      {
        "content": "김 김 왁왁 흑굳형 너무좋아",
        "writer": "Uggk2l9WQX4pZngCoAEC.8VKkiwUeJC98WkkTIMPkHE",
        "write_date": "2017-11-12",
        "url": "https://www.youtube.com/channel/UCBkyj16n2snkRg1BAzpovXQ",
        "parent_url": "https://www.youtube.com/watch?v=hi9nDUwwYWc",
        "source_site": "https://www.youtube.com/"
      },
      {
        "content": "너무너무 너무 아늑해요",
        "writer": "Uggk2l9WQX4pZngCoAEC.8VKkiwUeJC98WwHfITjYPa",
        "write_date": "2017-11-12",
        "url": "https://www.youtube.com/channel/UCBkyj16n2snkRg1BAzpovXQ",
        "parent_url": "https://www.youtube.com/watch?v=hi9nDUwwYWc",
        "source_site": "https://www.youtube.com/"
      },
      {
        "content": "(이름) 영상 고정광고에요진짜",
        "writer": "UgiGUt07oI32LXgCoAEC.8VKg-znOcjY8VKyVL8dvFf",
        "write_date": "2017-11-12",
        "url": "https://www.youtube.com/channel/UCBkyj16n2snkRg1BAzpovXQ",
        "parent_url": "https://www.youtube.com/watch?v=hi9nDUwwYWc",
        "source_site": "https://www.youtube.com/"
      },
      {
        "content": "(이름) 쉬어가면좋죠머",
        "writer": "UgiGUt07oI32LXgCoAEC.8VKg-znOcjY8VLhBZwenDT",
        "write_date": "2017-11-12",
        "url": "https://www.youtube.com/channel/UCBkyj16n2snkRg1BAzpovXQ",
        "parent_url": "https://www.youtube.com/watch?v=hi9nDUwwYWc",
        "source_site": "https://www.youtube.com/"
      },
      {
        "content": "(이름) 레드를 애용합시다",
        "writer": "UgiGUt07oI32LXgCoAEC.8VKg-znOcjY8VLoGMpzdf5",
        "write_date": "2017-11-12",
        "url": "https://www.youtube.com/channel/UCBkyj16n2snkRg1BAzpovXQ",
        "parent_url": "https://www.youtube.com/watch?v=hi9nDUwwYWc",
        "source_site": "https://www.youtube.com/"
      },
      {
        "content": "진짜 로다가 그 광고 부숴버리고싶음,",
        "writer": "UgiGUt07oI32LXgCoAEC.8VKg-znOcjY8VcsBEoRGXR",
        "write_date": "2017-11-12",
        "url": "https://www.youtube.com/channel/UCBkyj16n2snkRg1BAzpovXQ",
        "parent_url": "https://www.youtube.com/watch?v=hi9nDUwwYWc",
        "source_site": "https://www.youtube.com/"
      },
      {
        "content": "사실 이겜 존잼이지만 오늘하루만 스팀을 위해 노잼무새가 되겠어,",
        "writer": "Ugg93oUEvoOW53gCoAEC.8VK_LEg7tu_8VK_RbiV7ik",
        "write_date": "2017-11-12",
        "url": "https://www.youtube.com/channel/UCBkyj16n2snkRg1BAzpovXQ",
        "parent_url": "https://www.youtube.com/watch?v=hi9nDUwwYWc",
        "source_site": "https://www.youtube.com/"
      },
      {
        "content": "왜 말이많아",
        "writer": "UghZtPGKxxYuYHgCoAEC.8VKZvU79emA9GQaR4pJ3Xl",
        "write_date": "2020-12-12",
        "url": "https://www.youtube.com/channel/UCBkyj16n2snkRg1BAzpovXQ",
        "parent_url": "https://www.youtube.com/watch?v=hi9nDUwwYWc",
        "source_site": "https://www.youtube.com/"
      },
      {
        "content": "왁굳텽 목소리 너무 죠아",
        "writer": "Ugggw2Xl4naksHgCoAEC",
        "write_date": "2017-11-12",
        "url": "https://www.youtube.com/channel/UCBkyj16n2snkRg1BAzpovXQ",
        "parent_url": "https://www.youtube.com/watch?v=hi9nDUwwYWc",
        "source_site": "https://www.youtube.com/"
      },
      {
        "content": "쥐들도 한 가정의 가장이야 가장.",
        "writer": "UghaoAZBETLEzHgCoAEC",
        "write_date": "2017-11-12",
        "url": "https://www.youtube.com/channel/UCBkyj16n2snkRg1BAzpovXQ",
        "parent_url": "https://www.youtube.com/watch?v=hi9nDUwwYWc",
        "source_site": "https://www.youtube.com/"
      },
      {
        "content": "쥐(비속어)들은 지 몸뚱아리만한 치즈먹고 부족하다고 더달라하네",
        "writer": "UggSDfIf4hG1HHgCoAEC",
        "write_date": "2017-11-12",
        "url": "https://www.youtube.com/channel/UCBkyj16n2snkRg1BAzpovXQ",
        "parent_url": "https://www.youtube.com/watch?v=hi9nDUwwYWc",
        "source_site": "https://www.youtube.com/"
      },
      {
        "content": "형 안자",
        "writer": "UghMn-Z1Tb4uIHgCoAEC",
        "write_date": "2017-11-12",
        "url": "https://www.youtube.com/channel/UCBkyj16n2snkRg1BAzpovXQ",
        "parent_url": "https://www.youtube.com/watch?v=hi9nDUwwYWc",
        "source_site": "https://www.youtube.com/"
      },
      {
        "content": "쿠소, 인건가, 슬슬 구분이 안가,",
        "writer": "UggIMWGZYxp-EHgCoAEC",
        "write_date": "2017-11-12",
        "url": "https://www.youtube.com/channel/UCBkyj16n2snkRg1BAzpovXQ",
        "parent_url": "https://www.youtube.com/watch?v=hi9nDUwwYWc",
        "source_site": "https://www.youtube.com/"
      },
      {
        "content": "오쨩은 깝쭉거릴때가 제일 커여워",
        "writer": "UggUsrp82xCzRXgCoAEC",
        "write_date": "2017-11-12",
        "url": "https://www.youtube.com/channel/UCBkyj16n2snkRg1BAzpovXQ",
        "parent_url": "https://www.youtube.com/watch?v=hi9nDUwwYWc",
        "source_site": "https://www.youtube.com/"
      },
      {
        "content": "쥐(비속어)가 왁굳형 닮았어",
        "writer": "UgjHkCT_MSvWeXgCoAEC",
        "write_date": "2017-11-12",
        "url": "https://www.youtube.com/channel/UCBkyj16n2snkRg1BAzpovXQ",
        "parent_url": "https://www.youtube.com/watch?v=hi9nDUwwYWc",
        "source_site": "https://www.youtube.com/"
      },
      {
        "content": "음 한글화군요, 이게임은 몇 전철기죠,",
        "writer": "UgiopZfF56aYnngCoAEC",
        "write_date": "2017-11-12",
        "url": "https://www.youtube.com/channel/UCBkyj16n2snkRg1BAzpovXQ",
        "parent_url": "https://www.youtube.com/watch?v=hi9nDUwwYWc",
        "source_site": "https://www.youtube.com/"
      },
      {
        "content": "오프닝멘트 거진 묵음이죠",
        "writer": "Ugi5ldz_1cFdNXgCoAEC",
        "write_date": "2017-11-12",
        "url": "https://www.youtube.com/channel/UCBkyj16n2snkRg1BAzpovXQ",
        "parent_url": "https://www.youtube.com/watch?v=hi9nDUwwYWc",
        "source_site": "https://www.youtube.com/"
      },
      {
        "content": "앙 기머리",
        "writer": "UggxPwqVjvshRXgCoAEC",
        "write_date": "2017-11-12",
        "url": "https://www.youtube.com/channel/UCBkyj16n2snkRg1BAzpovXQ",
        "parent_url": "https://www.youtube.com/watch?v=hi9nDUwwYWc",
        "source_site": "https://www.youtube.com/"
      },
      {
        "content": "오늘은 이거다",
        "writer": "Ugj1RovTBQajSngCoAEC",
        "write_date": "2017-11-12",
        "url": "https://www.youtube.com/channel/UCBkyj16n2snkRg1BAzpovXQ",
        "parent_url": "https://www.youtube.com/watch?v=hi9nDUwwYWc",
        "source_site": "https://www.youtube.com/"
      },
      {
        "content": "안녕하세요 사랑하는 시청자여러분들 반갑습니다 우왁굳입니다 오늘여러분들게 보여드릴 게임은. 하는데 2초 안걸림",
        "writer": "Ugi4hxL7-nQBVHgCoAEC",
        "write_date": "2017-11-12",
        "url": "https://www.youtube.com/channel/UCBkyj16n2snkRg1BAzpovXQ",
        "parent_url": "https://www.youtube.com/watch?v=hi9nDUwwYWc",
        "source_site": "https://www.youtube.com/"
      },
      {
        "content": "앙 기다리고 있띠",
        "writer": "UggWNco1s6i7PHgCoAEC",
        "write_date": "2017-11-12",
        "url": "https://www.youtube.com/channel/UCBkyj16n2snkRg1BAzpovXQ",
        "parent_url": "https://www.youtube.com/watch?v=hi9nDUwwYWc",
        "source_site": "https://www.youtube.com/"
      },
      {
        "content": "방금 올(반사회적용어)건가보네 처리중 보고싶다",
        "writer": "UggtYOwqSsrBa3gCoAEC",
        "write_date": "2017-11-12",
        "url": "https://www.youtube.com/channel/UCBkyj16n2snkRg1BAzpovXQ",
        "parent_url": "https://www.youtube.com/watch?v=hi9nDUwwYWc",
        "source_site": "https://www.youtube.com/"
      },
      {
        "content": "반푼김 린민의 힘을 보여준 반푼띠",
        "writer": "UggUsrp82xCzRXgCoAEC.8VKUduKsbIb8Vg9V0AJlHd",
        "write_date": "2017-11-12",
        "url": "https://www.youtube.com/channel/UCBkyj16n2snkRg1BAzpovXQ",
        "parent_url": "https://www.youtube.com/watch?v=hi9nDUwwYWc",
        "source_site": "https://www.youtube.com/"
      },
      {
        "content": "왁두 전철깈",
        "writer": "UgiopZfF56aYnngCoAEC.8VKTSkADoYm8VL8510ETSu",
        "write_date": "2017-11-12",
        "url": "https://www.youtube.com/channel/UCBkyj16n2snkRg1BAzpovXQ",
        "parent_url": "https://www.youtube.com/watch?v=hi9nDUwwYWc",
        "source_site": "https://www.youtube.com/"
      },
      {
        "content": "왁두 무슨뜻",
        "writer": "UgiopZfF56aYnngCoAEC.8VKTSkADoYm8VLG0GtNB1s",
        "write_date": "2017-11-12",
        "url": "https://www.youtube.com/channel/UCBkyj16n2snkRg1BAzpovXQ",
        "parent_url": "https://www.youtube.com/watch?v=hi9nDUwwYWc",
        "source_site": "https://www.youtube.com/"
      },
      {
        "content": "야생 동물 경주가 이걸",
        "writer": "UgiopZfF56aYnngCoAEC.8VKTSkADoYm8VLGdkEWOr0",
        "write_date": "2017-11-12",
        "url": "https://www.youtube.com/channel/UCBkyj16n2snkRg1BAzpovXQ",
        "parent_url": "https://www.youtube.com/watch?v=hi9nDUwwYWc",
        "source_site": "https://www.youtube.com/"
      },
      {
        "content": "SODA YAHO (이름)이 예전에 10쿠소겜인 야생동물경주라는 게임을 하셨음. 친절하게도 그게임이 한글화가 되있었는데 사실상 번역기였음 거기서 돈이 전철기였음",
        "writer": "UgiopZfF56aYnngCoAEC.8VKTSkADoYm8VLIcnZS36c",
        "write_date": "2017-11-12",
        "url": "https://www.youtube.com/channel/UCBkyj16n2snkRg1BAzpovXQ",
        "parent_url": "https://www.youtube.com/watch?v=hi9nDUwwYWc",
        "source_site": "https://www.youtube.com/"
      },
      {
        "content": "하나의 (비속어)",
        "writer": "UgiopZfF56aYnngCoAEC.8VKTSkADoYm8VMWX7PYd12",
        "write_date": "2017-11-12",
        "url": "https://www.youtube.com/channel/UCBkyj16n2snkRg1BAzpovXQ",
        "parent_url": "https://www.youtube.com/watch?v=hi9nDUwwYWc",
        "source_site": "https://www.youtube.com/"
      },
      {
        "content": "왁두 앜 레전설급 쿠소겜",
        "writer": "UgiopZfF56aYnngCoAEC.8VKTSkADoYm8W2AgJMM4_U",
        "write_date": "2017-11-12",
        "url": "https://www.youtube.com/channel/UCBkyj16n2snkRg1BAzpovXQ",
        "parent_url": "https://www.youtube.com/watch?v=hi9nDUwwYWc",
        "source_site": "https://www.youtube.com/"
      },
      {
        "content": "잘못된 방법,",
        "writer": "UgiopZfF56aYnngCoAEC.8VKTSkADoYm92ZpEeWyv03",
        "write_date": "2020-11-12",
        "url": "https://www.youtube.com/channel/UCBkyj16n2snkRg1BAzpovXQ",
        "parent_url": "https://www.youtube.com/watch?v=hi9nDUwwYWc",
        "source_site": "https://www.youtube.com/"
      },
      {
        "content": "전철기 까먹고있다 갑자기 셍각났네",
        "writer": "UgiopZfF56aYnngCoAEC.8VKTSkADoYm97Hu8Tu_yiG",
        "write_date": "2020-11-12",
        "url": "https://www.youtube.com/channel/UCBkyj16n2snkRg1BAzpovXQ",
        "parent_url": "https://www.youtube.com/watch?v=hi9nDUwwYWc",
        "source_site": "https://www.youtube.com/"
      },
      {
        "content": "(이름) 랩퍼 왁두",
        "writer": "Ugi4hxL7-nQBVHgCoAEC.8VKOJ9uU_9h8VKueMKgOsS",
        "write_date": "2017-11-12",
        "url": "https://www.youtube.com/channel/UCBkyj16n2snkRg1BAzpovXQ",
        "parent_url": "https://www.youtube.com/watch?v=hi9nDUwwYWc",
        "source_site": "https://www.youtube.com/"
      },
      {
        "content": "이거 갓겜 꿀잼 진짜루",
        "writer": "UgjRoKjAwyx773gCoAEC",
        "write_date": "2017-11-12",
        "url": "https://www.youtube.com/channel/UCBkyj16n2snkRg1BAzpovXQ",
        "parent_url": "https://www.youtube.com/watch?v=hi9nDUwwYWc",
        "source_site": "https://www.youtube.com/"
      }
    ]
  }
}